lmchunker/__init__.py
lmchunker/chunker.py
lmchunker/modules/__init__.py
lmchunker/modules/dense_x_retrieval.py
lmchunker/modules/lumberchunker.py
lmchunker/modules/lumberchunker_margin_sampling.py
lmchunker/modules/margin_sampling_chunking.py
lmchunker/modules/ppl_chunking.py
lmchunker/utils/ppl_calculate.py
lmchunker-0.5.1.dist-info/METADATA
lmchunker-0.5.1.dist-info/WHEEL
lmchunker-0.5.1.dist-info/RECORD
