Metadata-Version: 2.3
Name: lmchunker
Version: 0.5.1
Summary: We intend to develop this project into a plug-and-play chunking library that incorporates various cutting-edge chunking strategies for LLMs.
License: Apache-2.0
Author: Robot2050
Requires-Python: >=3.10,<4.0
Classifier: License :: OSI Approved :: Apache Software License
Classifier: Programming Language :: Python :: 3
Classifier: Programming Language :: Python :: 3.10
Classifier: Programming Language :: Python :: 3.11
Classifier: Programming Language :: Python :: 3.12
Classifier: Programming Language :: Python :: 3.13
Requires-Dist: ipykernel (>=6.29.5,<7.0.0)
Requires-Dist: jieba (>=0.42.1,<0.43.0)
Requires-Dist: nltk (==3.8.1)
Requires-Dist: pandas (>=2.2.3,<3.0.0)
Requires-Dist: protobuf (>=5.28.3,<6.0.0)
Requires-Dist: sentencepiece (>=0.2.0,<0.3.0)
Requires-Dist: tiktoken (>=0.8.0,<0.9.0)
Requires-Dist: torch (>=2.5.1,<3.0.0)
Requires-Dist: transformers (>=4.46.3,<5.0.0)
Requires-Dist: zhipuai (>=2.1.5.20230904,<3.0.0.0)
